MANIFEST.in
README.txt
requirements.txt
setup.py
sesamclient/VERSION.txt
sesamclient/__init__.py
sesamclient/connection.py
sesamclient/dataset.py
sesamclient/entity_json.py
sesamclient/entitybase.py
sesamclient/exceptions.py
sesamclient/log.py
sesamclient/model.py
sesamclient/pipe.py
sesamclient/pump.py
sesamclient/system.py
sesamclient/utils.py
sesamclient.egg-info/PKG-INFO
sesamclient.egg-info/SOURCES.txt
sesamclient.egg-info/dependency_links.txt
sesamclient.egg-info/entry_points.txt
sesamclient.egg-info/not-zip-safe
sesamclient.egg-info/requires.txt
sesamclient.egg-info/top_level.txt
sesamclient/main/__init__.py
sesamclient/main/main.py
sesamclient/main/utils.py
sesamclient/main/commands/__init__.py
sesamclient/main/commands/config.py
sesamclient/main/commands/datasets.py
sesamclient/main/commands/envvarsmanager.py
sesamclient/main/commands/export.py
sesamclient/main/commands/import_cmd.py
sesamclient/main/commands/license.py
sesamclient/main/commands/login.py
sesamclient/main/commands/logs.py
sesamclient/main/commands/pipes.py
sesamclient/main/commands/pumps.py
sesamclient/main/commands/secretsmanager.py
sesamclient/main/commands/systems.py
sesamclient/tests/__init__.py
sesamclient/tests/test_export_command.py