Metadata-Version: 1.1
Name: sesamclient
Version: 0.2.120
Summary: sesamapi client
Home-page: http://sesam.io
Author: Sesam
Author-email: UNKNOWN
License: UNKNOWN
Platform: UNKNOWN
Classifier: Programming Language :: Python
Classifier: Topic :: Internet :: WWW/HTTP
